latitude_cli/__init__.py
latitude_cli/cli.py
latitude_cli/libs/template.py
latitude_cli/libs/version.py
latitude_cli/modules/templates.py
latitude_cli-0.9.0.dist-info/METADATA
latitude_cli-0.9.0.dist-info/WHEEL
latitude_cli-0.9.0.dist-info/entry_points.txt
latitude_cli-0.9.0.dist-info/RECORD
