Metadata-Version: 2.1
Name: latitude-cli
Version: 0.9.0
Summary: CLI for managing some general dev tasks
Home-page: https://github.com/hloughrey/latitude-cli
Author: Hugh Loughrey
Author-email: hugh.loughrey@gmail.com
Requires-Python: >=3.8.1,<4.0
Classifier: Programming Language :: Python :: 3
Classifier: Programming Language :: Python :: 3.9
Classifier: Programming Language :: Python :: 3.10
Classifier: Programming Language :: Python :: 3.11
Requires-Dist: GitPython (>=3.1.32,<4.0.0)
Requires-Dist: asyncio (>=3.4.3,<4.0.0)
Requires-Dist: colorama (>=0.4.4,<0.5.0)
Requires-Dist: httpx (>=0.25.1,<0.26.0)
Requires-Dist: packaging (>=21.3,<22.0)
Requires-Dist: shellingham (>=1.4.0,<2.0.0)
Requires-Dist: typer (>=0.4.0,<0.5.0)
Project-URL: Repository, https://github.com/hloughrey/latitude-cli
